qwiic_max3010x/__init__.py
qwiic_max3010x/heart_rate.py
qwiic_max3010x/qwiic_max3010x.py
sparkfun_qwiic_max3010x-0.0.2.dist-info/LICENSE
sparkfun_qwiic_max3010x-0.0.2.dist-info/METADATA
sparkfun_qwiic_max3010x-0.0.2.dist-info/WHEEL
sparkfun_qwiic_max3010x-0.0.2.dist-info/top_level.txt
sparkfun_qwiic_max3010x-0.0.2.dist-info/RECORD
